Metadata-Version: 2.1
Name: poetry-demo-taurus
Version: 0.1.0
Summary: 
Author: 袁郑
Author-email: yzheng@epoint.com.cn
Requires-Python: >=3.10,<4.0
Classifier: Programming Language :: Python :: 3
Classifier: Programming Language :: Python :: 3.10
Classifier: Programming Language :: Python :: 3.11
Requires-Dist: loguru (>=0.6.0,<0.7.0)
